trellis/__init__.py
trellis/datasets/__init__.py
trellis/datasets/components.py
trellis/datasets/sparse_feat2render.py
trellis/datasets/sparse_structure.py
trellis/datasets/sparse_structure_latent.py
trellis/datasets/structured_latent.py
trellis/datasets/structured_latent2render.py
trellis/models/__init__.py
trellis/models/sparse_elastic_mixin.py
trellis/models/sparse_structure_flow.py
trellis/models/sparse_structure_vae.py
trellis/models/structured_latent_flow.py
trellis/models/structured_latent_vae/__init__.py
trellis/models/structured_latent_vae/base.py
trellis/models/structured_latent_vae/decoder_gs.py
trellis/models/structured_latent_vae/decoder_mesh.py
trellis/models/structured_latent_vae/decoder_rf.py
trellis/models/structured_latent_vae/encoder.py
trellis/pipelines/__init__.py
trellis/pipelines/base.py
trellis/pipelines/trellis_image_to_3d.py
trellis/pipelines/trellis_text_to_3d.py
trellis/pipelines/samplers/__init__.py
trellis/pipelines/samplers/base.py
trellis/pipelines/samplers/classifier_free_guidance_mixin.py
trellis/pipelines/samplers/flow_euler.py
trellis/pipelines/samplers/guidance_interval_mixin.py
trellis/renderers/__init__.py
trellis/renderers/gaussian_render.py
trellis/renderers/mesh_renderer.py
trellis/renderers/octree_renderer.py
trellis/renderers/sh_utils.py
trellis/representations/__init__.py
trellis/representations/gaussian/__init__.py
trellis/representations/gaussian/gaussian_model.py
trellis/representations/gaussian/general_utils.py
trellis/representations/mesh/__init__.py
trellis/representations/mesh/cube2mesh.py
trellis/representations/mesh/utils_cube.py
trellis/representations/octree/__init__.py
trellis/representations/octree/octree_dfs.py
trellis/representations/radiance_field/__init__.py
trellis/representations/radiance_field/strivec.py
trellis/trainers/__init__.py
trellis/trainers/base.py
trellis/trainers/basic.py
trellis/trainers/utils.py
trellis/utils/__init__.py
trellis/utils/data_utils.py
trellis/utils/dist_utils.py
trellis_3d-0.1.0.dist-info/LICENSE
trellis_3d-0.1.0.dist-info/METADATA
trellis_3d-0.1.0.dist-info/WHEEL
trellis_3d-0.1.0.dist-info/top_level.txt
trellis_3d-0.1.0.dist-info/RECORD
