Metadata-Version: 2.2
Name: trellis-3d
Version: 0.1.0
Summary: TRELLIS is a large 3D asset generation model.
Home-page: https://github.com/microsoft/trellis
Author: Microsoft Corporation
Author-email: t-jxiang@microsoft.com
License: MIT
Classifier: Programming Language :: Python :: 3
Classifier: License :: OSI Approved :: MIT License
Classifier: Operating System :: OS Independent
Requires-Python: >=3.8
License-File: LICENSE
Requires-Dist: torch
Requires-Dist: numpy
Requires-Dist: pillow
Dynamic: author
Dynamic: author-email
Dynamic: classifier
Dynamic: description
Dynamic: description-content-type
Dynamic: home-page
Dynamic: license
Dynamic: requires-dist
Dynamic: requires-python
Dynamic: summary
